{
  "Songs": [
    {
      "Order": 1,
      "Name": "FLARE (TV Size)",
      "Artist": "Void_Chords feat. LIO",
      "Path": "1000078 Void_Chords feat LIO - FLARE (TV Size)\\audio.mp3"
    },
    {
      "Order": 2,
      "Name": "Itsuka Sekai ga Kawaru made (TV Size)",
      "Artist": "Iida Riho",
      "Path": "1001372 Iida Riho - Itsuka Sekai ga Kawaru made (TV Size)\\audio.mp3"
    },
    {
      "Order": 3,
      "Name": "Ao no Kanata (TV Size)",
      "Artist": "Suzuki Konomi",
      "Path": "1003234 Suzuki Konomi - Ao no Kanata (TV Size)\\audio.mp3"
    },
    {
      "Order": 4,
      "Name": "Boku o Mitsukete (TV Size)",
      "Artist": "fhana",
      "Path": "1003728 fhana - Boku o Mitsukete (TV Size)\\audio.mp3"
    },
    {
      "Order": 5,
      "Name": "Kanade (TV Size)",
      "Artist": "Takagi-san (CV: Takahashi Rie)",
      "Path": "1004335 Takagi-san (CV- Takahashi Rie) - Kanade (TV Size)\\kanade.mp3"
    }
  ]
}